[
  {
    "icao"      : "a1530a",
    "callsign"  : "DCM4121",
    "nnumber"   : "N1848T",
    "departure" :
    {
      "airport"             : "KPPQ",
      "time"                : "2019-12-02 11:55:50+00:00",
      "airport_position"    : 
      {
        "altitude"  : "710.0",
        "latitude"  : "39.63890075683594",
        "longitude" : "-90.77839660644531"
      },
      "aircraft_position"   : 
      {
        "altitude"  : "3549.9999999999995",
        "latitude"  : "39.6492919921875",
        "longitude" : "-90.82928864852244"
      },
      "horizontal_distance" : "4518.130725530701",
      "vertical_distance"   : "2839.9999999999995"
    },
    "arrival"   :
    {
      "airport"             : "KPDK",
      "time"                : "2019-12-02 12:56:29+00:00",
      "airport_position"    : 
      {
        "altitude"  : "1003.0",
        "latitude"  : "33.8755989075",
        "longitude" : "-84.3020019531"
      },
      "aircraft_position"   : 
      {
        "altitude"  : "1175.0",
        "latitude"  : "33.862106323242195",
        "longitude" : "-84.3069520288584"
      },
      "horizontal_distance" : "1565.1136912869174",
      "vertical_distance"   : "172.0"
    }
  },
  {
    "icao"      : "a1530a",
    "callsign"  : "DCM4121",
    "nnumber"   : "N1848T",
    "departure" :
    {
      "airport"             : "KPDK",
      "time"                : "2019-12-02 13:58:30+00:00",
      "airport_position"    : 
      {
        "altitude"  : "1003.0",
        "latitude"  : "33.8755989075",
        "longitude" : "-84.3020019531"
      },
      "aircraft_position"   : 
      {
        "altitude"  : "4175.0",
        "latitude"  : "33.95143153303761",
        "longitude" : "-84.29271697998047"
      },
      "horizontal_distance" : "8455.130789001234",
      "vertical_distance"   : "3172.0"
    },
    "arrival"   :
    {
      "airport"             : "KPPQ",
      "time"                : "2019-12-02 15:17:21+00:00",
      "airport_position"    : 
      {
        "altitude"  : "710.0",
        "latitude"  : "39.63890075683594",
        "longitude" : "-90.77839660644531"
      },
      "aircraft_position"   : 
      {
        "altitude"  : "3575.0",
        "latitude"  : "39.693603515625",
        "longitude" : "-90.87042236328124"
      },
      "horizontal_distance" : "9962.110053835193",
      "vertical_distance"   : "2865.0"
    }
  },
  {
    "icao"      : "a1530a",
    "callsign"  : "DCM4121",
    "nnumber"   : "N1848T",
    "departure" :
    {
      "airport"             : "9LL0",
      "time"                : "2019-12-02 21:24:04+00:00",
      "airport_position"    : 
      {
        "altitude"  : "715.0",
        "latitude"  : "39.81999969482422",
        "longitude" : "-91.22100067138672"
      },
      "aircraft_position"   : 
      {
        "altitude"  : "7050.0",
        "latitude"  : "39.84246826171875",
        "longitude" : "-91.15177320397422"
      },
      "horizontal_distance" : "6429.821212695649",
      "vertical_distance"   : "6335.0"
    },
    "arrival"   :
    {
      "airport"             : "KPDK",
      "time"                : "2019-12-02 22:25:29+00:00",
      "airport_position"    : 
      {
        "altitude"  : "1003.0",
        "latitude"  : "33.8755989075",
        "longitude" : "-84.3020019531"
      },
      "aircraft_position"   : 
      {
        "altitude"  : "1474.9999999999998",
        "latitude"  : "33.844501042770126",
        "longitude" : "-84.31440353393555"
      },
      "horizontal_distance" : "3635.2618123164857",
      "vertical_distance"   : "471.9999999999998"
    }
  },
  {
    "icao"      : "a1530a",
    "callsign"  : "DCM4121",
    "nnumber"   : "N1848T",
    "departure" :
    {
      "airport"             : "KPDK",
      "time"                : "2019-12-02 22:52:16+00:00",
      "airport_position"    : 
      {
        "altitude"  : "1003.0",
        "latitude"  : "33.8755989075",
        "longitude" : "-84.3020019531"
      },
      "aircraft_position"   : 
      {
        "altitude"  : "3499.9999999999995",
        "latitude"  : "33.91837944418697",
        "longitude" : "-84.30501937866211"
      },
      "horizontal_distance" : "4753.440482780709",
      "vertical_distance"   : "2496.9999999999995"
    },
    "arrival"   :
    {
      "airport"             : "51IS",
      "time"                : "2019-12-03 00:11:25+00:00",
      "airport_position"    : 
      {
        "altitude"  : "620.0",
        "latitude"  : "39.65919876098633",
        "longitude" : "-90.70010375976562"
      },
      "aircraft_position"   : 
      {
        "altitude"  : "2000.0",
        "latitude"  : "39.58550921941207",
        "longitude" : "-90.70947265625"
      },
      "horizontal_distance" : "8221.009239137575",
      "vertical_distance"   : "1380.0"
    }
  },
  {
    "icao"      : "a1530a",
    "callsign"  : "DCM4121",
    "nnumber"   : "N1848T",
    "departure" :
    {
      "airport"             : "KUIN",
      "time"                : "2019-12-03 13:06:00+00:00",
      "airport_position"    : 
      {
        "altitude"  : "768.0",
        "latitude"  : "39.94269943",
        "longitude" : "-91.19460297"
      },
      "aircraft_position"   : 
      {
        "altitude"  : "6225.0",
        "latitude"  : "39.9580667786679",
        "longitude" : "-90.99382573908024"
      },
      "horizontal_distance" : "17242.176684350627",
      "vertical_distance"   : "5457.0"
    },
    "arrival"   :
    {
      "airport"             : "KISP",
      "time"                : "2019-12-03 15:15:58+00:00",
      "airport_position"    : 
      {
        "altitude"  : "99.0",
        "latitude"  : "40.79520035",
        "longitude" : "-73.10019684"
      },
      "aircraft_position"   : 
      {
        "altitude"  : "700.0",
        "latitude"  : "40.78720868644068",
        "longitude" : "-73.08767145330256"
      },
      "horizontal_distance" : "1380.2763211512854",
      "vertical_distance"   : "601.0"
    }
  },
  {
    "icao"      : "a1530a",
    "callsign"  : "DCM4121",
    "nnumber"   : "N1848T",
    "departure" :
    {
      "airport"             : "KISP",
      "time"                : "2019-12-03 22:15:09+00:00",
      "airport_position"    : 
      {
        "altitude"  : "99.0",
        "latitude"  : "40.79520035",
        "longitude" : "-73.10019684"
      },
      "aircraft_position"   : 
      {
        "altitude"  : "1025.0",
        "latitude"  : "40.8057861328125",
        "longitude" : "-73.11175537109375"
      },
      "horizontal_distance" : "1527.5267319920663",
      "vertical_distance"   : "926.0"
    },
    "arrival"   :
    {
      "airport"             : "KI63",
      "time"                : "2019-12-04 00:22:58+00:00",
      "airport_position"    : 
      {
        "altitude"  : "734.0",
        "latitude"  : "39.98749924",
        "longitude" : "-90.80419922"
      },
      "aircraft_position"   : 
      {
        "altitude"  : "5150.0",
        "latitude"  : "39.9931206137447",
        "longitude" : "-90.8448860862038"
      },
      "horizontal_distance" : "3530.511243218901",
      "vertical_distance"   : "4416.0"
    }
  },
  {
    "icao"      : "a1530a",
    "callsign"  : "DCM4121",
    "nnumber"   : "N1848T",
    "departure" :
    {
      "airport"             : "KPPQ",
      "time"                : "2019-12-04 12:57:40+00:00",
      "airport_position"    : 
      {
        "altitude"  : "710.0",
        "latitude"  : "39.63890075683594",
        "longitude" : "-90.77839660644531"
      },
      "aircraft_position"   : 
      {
        "altitude"  : "3025.0",
        "latitude"  : "39.64514263605667",
        "longitude" : "-90.84716796875"
      },
      "horizontal_distance" : "5943.743496661405",
      "vertical_distance"   : "2315.0"
    },
    "arrival"   :
    {
      "airport"             : "KX49",
      "time"                : "2019-12-04 14:37:50+00:00",
      "airport_position"    : 
      {
        "altitude"  : "110.0",
        "latitude"  : "27.93339920043945",
        "longitude" : "-82.04399871826172"
      },
      "aircraft_position"   : 
      {
        "altitude"  : "525.0",
        "latitude"  : "27.95169067382812",
        "longitude" : "-82.0556171123798"
      },
      "horizontal_distance" : "2327.285844747285",
      "vertical_distance"   : "415.0"
    }
  },
  {
    "icao"      : "a1530a",
    "callsign"  : "DCM4121",
    "nnumber"   : "N1848T",
    "departure" :
    {
      "airport"             : "KLAL",
      "time"                : "2019-12-04 15:52:39+00:00",
      "airport_position"    : 
      {
        "altitude"  : "142.0",
        "latitude"  : "27.988899",
        "longitude" : "-82.018602"
      },
      "aircraft_position"   : 
      {
        "altitude"  : "1050.0",
        "latitude"  : "28.010388390492576",
        "longitude" : "-81.99888341567096"
      },
      "horizontal_distance" : "3071.3470574777207",
      "vertical_distance"   : "908.0"
    },
    "arrival"   :
    {
      "airport"             : "44IS",
      "time"                : "2019-12-04 18:05:17+00:00",
      "airport_position"    : 
      {
        "altitude"  : "700.0",
        "latitude"  : "39.74480056762695",
        "longitude" : "-91.07489776611328"
      },
      "aircraft_position"   : 
      {
        "altitude"  : "4050.0",
        "latitude"  : "39.76831985732257",
        "longitude" : "-90.99139404296876"
      },
      "horizontal_distance" : "7617.540220195336",
      "vertical_distance"   : "3350.0"
    }
  },
  {
    "icao"      : "a1530a",
    "callsign"  : "DCM4121",
    "nnumber"   : "N1848T",
    "departure" :
    {
      "airport"             : "KPPQ",
      "time"                : "2019-12-05 12:13:42+00:00",
      "airport_position"    : 
      {
        "altitude"  : "710.0",
        "latitude"  : "39.63890075683594",
        "longitude" : "-90.77839660644531"
      },
      "aircraft_position"   : 
      {
        "altitude"  : "3449.9999999999995",
        "latitude"  : "39.57861948821504",
        "longitude" : "-90.73101806640624"
      },
      "horizontal_distance" : "7832.605257510745",
      "vertical_distance"   : "2739.9999999999995"
    },
    "arrival"   :
    {
      "airport"             : "KBHM",
      "time"                : "2019-12-05 13:04:57+00:00",
      "airport_position"    : 
      {
        "altitude"  : "650.0",
        "latitude"  : "33.56290054",
        "longitude" : "-86.75350189"
      },
      "aircraft_position"   : 
      {
        "altitude"  : "8675.0",
        "latitude"  : "33.522811889648445",
        "longitude" : "-86.97304687499997"
      },
      "horizontal_distance" : "20869.778362511715",
      "vertical_distance"   : "8025.0"
    }
  },
  {
    "icao"      : "a1530a",
    "callsign"  : "DCM4121",
    "nnumber"   : "N1848T",
    "departure" :
    {
      "airport"             : "None",
      "time"                : "2019-12-05 13:55:42+00:00",
      "airport_position"    : "None",
      "aircraft_position"   : 
      {
        "altitude"  : "11799.999999999998",
        "latitude"  : "33.4457811258607",
        "longitude" : "-86.89423230229592"
      },
      "horizontal_distance" : "None",
      "vertical_distance"   : "None"
    },
    "arrival"   :
    {
      "airport"             : "44IS",
      "time"                : "2019-12-05 15:02:41+00:00",
      "airport_position"    : 
      {
        "altitude"  : "700.0",
        "latitude"  : "39.74480056762695",
        "longitude" : "-91.07489776611328"
      },
      "aircraft_position"   : 
      {
        "altitude"  : "5024.999999999999",
        "latitude"  : "39.87094116210938",
        "longitude" : "-91.07934702997622"
      },
      "horizontal_distance" : "14010.690512884958",
      "vertical_distance"   : "4324.999999999999"
    }
  },
  {
    "icao"      : "a1530a",
    "callsign"  : "DCM4121",
    "nnumber"   : "N1848T",
    "departure" :
    {
      "airport"             : "None",
      "time"                : "2019-12-05 15:51:41+00:00",
      "airport_position"    : "None",
      "aircraft_position"   : 
      {
        "altitude"  : "14900.0",
        "latitude"  : "40.20456087791313",
        "longitude" : "-91.33614973588423"
      },
      "horizontal_distance" : "None",
      "vertical_distance"   : "None"
    },
    "arrival"   :
    {
      "airport"             : "5MN0",
      "time"                : "2019-12-05 16:25:58+00:00",
      "airport_position"    : 
      {
        "altitude"  : "1280.0",
        "latitude"  : "43.866600036621094",
        "longitude" : "-92.56109619140624"
      },
      "aircraft_position"   : 
      {
        "altitude"  : "4024.9999999999995",
        "latitude"  : "43.87720657607256",
        "longitude" : "-92.64149257114956"
      },
      "horizontal_distance" : "6568.725140751416",
      "vertical_distance"   : "2744.9999999999995"
    }
  },
  {
    "icao"      : "a1530a",
    "callsign"  : "DCM4121",
    "nnumber"   : "N1848T",
    "departure" :
    {
      "airport"             : "7MN3",
      "time"                : "2019-12-05 16:55:03+00:00",
      "airport_position"    : 
      {
        "altitude"  : "1340.0",
        "latitude"  : "43.7052001953125",
        "longitude" : "-92.46070098876952"
      },
      "aircraft_position"   : 
      {
        "altitude"  : "5050.0",
        "latitude"  : "43.785219354144594",
        "longitude" : "-92.51776559012276"
      },
      "horizontal_distance" : "10008.611305628046",
      "vertical_distance"   : "3710.0"
    },
    "arrival"   :
    {
      "airport"             : "None",
      "time"                : "2019-12-05 17:15:57+00:00",
      "airport_position"    : "None",
      "aircraft_position"   : 
      {
        "altitude"  : "10974.999999999998",
        "latitude"  : "41.65278625488281",
        "longitude" : "-91.7633056640625"
      },
      "horizontal_distance" : "None",
      "vertical_distance"   : "None"
    }
  },
  {
    "icao"      : "a1530a",
    "callsign"  : "DCM4121",
    "nnumber"   : "N1848T",
    "departure" :
    {
      "airport"             : "9LL0",
      "time"                : "2019-12-05 20:54:23+00:00",
      "airport_position"    : 
      {
        "altitude"  : "715.0",
        "latitude"  : "39.81999969482422",
        "longitude" : "-91.22100067138672"
      },
      "aircraft_position"   : 
      {
        "altitude"  : "7150.0",
        "latitude"  : "39.797607421875",
        "longitude" : "-91.11087301503055"
      },
      "horizontal_distance" : "9752.631762404859",
      "vertical_distance"   : "6435.0"
    },
    "arrival"   :
    {
      "airport"             : "KEKY",
      "time"                : "2019-12-05 21:47:24+00:00",
      "airport_position"    : 
      {
        "altitude"  : "700.0",
        "latitude"  : "33.31290054",
        "longitude" : "-86.92590332"
      },
      "aircraft_position"   : 
      {
        "altitude"  : "8875.0",
        "latitude"  : "33.518966674804695",
        "longitude" : "-86.98694458007809"
      },
      "horizontal_distance" : "23549.82547597082",
      "vertical_distance"   : "8175.0"
    }
  },
  {
    "icao"      : "a1530a",
    "callsign"  : "DCM4121",
    "nnumber"   : "N1848T",
    "departure" :
    {
      "airport"             : "KEET",
      "time"                : "2019-12-05 22:14:10+00:00",
      "airport_position"    : 
      {
        "altitude"  : "586.0",
        "latitude"  : "33.17699814",
        "longitude" : "-86.78279877"
      },
      "aircraft_position"   : 
      {
        "altitude"  : "6150.0",
        "latitude"  : "33.168228149414055",
        "longitude" : "-86.69338989257812"
      },
      "horizontal_distance" : "8395.770734555314",
      "vertical_distance"   : "5564.0"
    },
    "arrival"   :
    {
      "airport"             : "None",
      "time"                : "2019-12-05 22:53:45+00:00",
      "airport_position"    : "None",
      "aircraft_position"   : 
      {
        "altitude"  : "8799.999999999998",
        "latitude"  : "34.716052039194906",
        "longitude" : "-81.25288009643555"
      },
      "horizontal_distance" : "None",
      "vertical_distance"   : "None"
    }
  },
  {
    "icao"      : "a1530a",
    "callsign"  : "DCM4121",
    "nnumber"   : "N1848T",
    "departure" :
    {
      "airport"             : "None",
      "time"                : "2019-12-06 13:27:00+00:00",
      "airport_position"    : "None",
      "aircraft_position"   : 
      {
        "altitude"  : "16550.000000000004",
        "latitude"  : "35.168819104210804",
        "longitude" : "-80.6817626953125"
      },
      "horizontal_distance" : "None",
      "vertical_distance"   : "None"
    },
    "arrival"   :
    {
      "airport"             : "2IL4",
      "time"                : "2019-12-06 14:54:11+00:00",
      "airport_position"    : 
      {
        "altitude"  : "590.0",
        "latitude"  : "39.77920150756836",
        "longitude" : "-90.74859619140624"
      },
      "aircraft_position"   : 
      {
        "altitude"  : "3549.9999999999995",
        "latitude"  : "39.77389526367188",
        "longitude" : "-90.92852385147758"
      },
      "horizontal_distance" : "15425.933857256223",
      "vertical_distance"   : "2959.9999999999995"
    }
  },
  {
    "icao"      : "a1530a",
    "callsign"  : "DCM4121",
    "nnumber"   : "N1848T",
    "departure" :
    {
      "airport"             : "KUIN",
      "time"                : "2019-12-06 20:46:45+00:00",
      "airport_position"    : 
      {
        "altitude"  : "768.0",
        "latitude"  : "39.94269943",
        "longitude" : "-91.19460297"
      },
      "aircraft_position"   : 
      {
        "altitude"  : "5100.0",
        "latitude"  : "39.91970773470604",
        "longitude" : "-91.0494384765625"
      },
      "horizontal_distance" : "12668.465199063958",
      "vertical_distance"   : "4332.0"
    },
    "arrival"   :
    {
      "airport"             : "KSVH",
      "time"                : "2019-12-06 21:55:50+00:00",
      "airport_position"    : 
      {
        "altitude"  : "968.0",
        "latitude"  : "35.765300750732",
        "longitude" : "-80.953903198242"
      },
      "aircraft_position"   : 
      {
        "altitude"  : "5400.0",
        "latitude"  : "35.760730808064096",
        "longitude" : "-80.78685354679189"
      },
      "horizontal_distance" : "15115.252108840177",
      "vertical_distance"   : "4432.0"
    }
  },
  {
    "icao"      : "a1530a",
    "callsign"  : "DCM4121",
    "nnumber"   : "N1848T",
    "departure" :
    {
      "airport"             : "None",
      "time"                : "2019-12-06 22:43:59+00:00",
      "airport_position"    : "None",
      "aircraft_position"   : 
      {
        "altitude"  : "11100.0",
        "latitude"  : "35.29518127441406",
        "longitude" : "-80.78052520751953"
      },
      "horizontal_distance" : "None",
      "vertical_distance"   : "None"
    },
    "arrival"   :
    {
      "airport"             : "51IS",
      "time"                : "2019-12-07 00:09:14+00:00",
      "airport_position"    : 
      {
        "altitude"  : "620.0",
        "latitude"  : "39.65919876098633",
        "longitude" : "-90.70010375976562"
      },
      "aircraft_position"   : 
      {
        "altitude"  : "1625.0",
        "latitude"  : "39.5900247864804",
        "longitude" : "-90.7152099609375"
      },
      "horizontal_distance" : "7788.956489133707",
      "vertical_distance"   : "1005.0"
    }
  },
  {
    "icao"      : "a1530a",
    "callsign"  : "DCM4121",
    "nnumber"   : "N1848T",
    "departure" :
    {
      "airport"             : "None",
      "time"                : "2019-12-09 16:22:23+00:00",
      "airport_position"    : "None",
      "aircraft_position"   : 
      {
        "altitude"  : "6674.999999999999",
        "latitude"  : "39.82283020019531",
        "longitude" : "-91.12060546875"
      },
      "horizontal_distance" : "None",
      "vertical_distance"   : "None"
    },
    "arrival"   :
    {
      "airport"             : "KLAL",
      "time"                : "2019-12-09 18:09:58+00:00",
      "airport_position"    : 
      {
        "altitude"  : "142.0",
        "latitude"  : "27.988899",
        "longitude" : "-82.018602"
      },
      "aircraft_position"   : 
      {
        "altitude"  : "300.0",
        "latitude"  : "28.01683044433594",
        "longitude" : "-81.98663564828723"
      },
      "horizontal_distance" : "4412.152979449266",
      "vertical_distance"   : "158.0"
    }
  },
  {
    "icao"      : "a1530a",
    "callsign"  : "DCM4121",
    "nnumber"   : "N1848T",
    "departure" :
    {
      "airport"             : "KX49",
      "time"                : "2019-12-09 18:50:02+00:00",
      "airport_position"    : 
      {
        "altitude"  : "110.0",
        "latitude"  : "27.93339920043945",
        "longitude" : "-82.04399871826172"
      },
      "aircraft_position"   : 
      {
        "altitude"  : "1875.0",
        "latitude"  : "27.956155033434854",
        "longitude" : "-82.0795575310202"
      },
      "horizontal_distance" : "4313.375245569013",
      "vertical_distance"   : "1765.0"
    },
    "arrival"   :
    {
      "airport"             : "51IS",
      "time"                : "2019-12-09 20:59:08+00:00",
      "airport_position"    : 
      {
        "altitude"  : "620.0",
        "latitude"  : "39.65919876098633",
        "longitude" : "-90.70010375976562"
      },
      "aircraft_position"   : 
      {
        "altitude"  : "2425.0",
        "latitude"  : "39.58387989108845",
        "longitude" : "-90.7073974609375"
      },
      "horizontal_distance" : "8385.873443027425",
      "vertical_distance"   : "1805.0"
    }
  },
  {
    "icao"      : "a1530a",
    "callsign"  : "DCM4121",
    "nnumber"   : "N1848T",
    "departure" :
    {
      "airport"             : "51IS",
      "time"                : "2019-12-10 21:52:40+00:00",
      "airport_position"    : 
      {
        "altitude"  : "620.0",
        "latitude"  : "39.65919876098633",
        "longitude" : "-90.70010375976562"
      },
      "aircraft_position"   : 
      {
        "altitude"  : "4325.0",
        "latitude"  : "39.68367004394531",
        "longitude" : "-90.69625854492188"
      },
      "horizontal_distance" : "2736.963728297871",
      "vertical_distance"   : "3705.0"
    },
    "arrival"   :
    {
      "airport"             : "KBWI",
      "time"                : "2019-12-10 23:17:44+00:00",
      "airport_position"    : 
      {
        "altitude"  : "146.0",
        "latitude"  : "39.1754",
        "longitude" : "-76.668297"
      },
      "aircraft_position"   : 
      {
        "altitude"  : "350.0",
        "latitude"  : "39.163373526880285",
        "longitude" : "-76.64129638671875"
      },
      "horizontal_distance" : "2688.367375061631",
      "vertical_distance"   : "204.0"
    }
  },
  {
    "icao"      : "a1530a",
    "callsign"  : "DCM4121",
    "nnumber"   : "N1848T",
    "departure" :
    {
      "airport"             : "KBWI",
      "time"                : "2019-12-11 12:45:13+00:00",
      "airport_position"    : 
      {
        "altitude"  : "146.0",
        "latitude"  : "39.1754",
        "longitude" : "-76.668297"
      },
      "aircraft_position"   : 
      {
        "altitude"  : "449.99999999999994",
        "latitude"  : "39.19569396972656",
        "longitude" : "-76.67083740234375"
      },
      "horizontal_distance" : "2263.6828795606116",
      "vertical_distance"   : "303.99999999999994"
    },
    "arrival"   :
    {
      "airport"             : "KI63",
      "time"                : "2019-12-11 14:39:40+00:00",
      "airport_position"    : 
      {
        "altitude"  : "734.0",
        "latitude"  : "39.98749924",
        "longitude" : "-90.80419922"
      },
      "aircraft_position"   : 
      {
        "altitude"  : "4350.0",
        "latitude"  : "39.98963928222656",
        "longitude" : "-90.85113525390624"
      },
      "horizontal_distance" : "4015.7534439921997",
      "vertical_distance"   : "3616.0"
    }
  },
  {
    "icao"      : "a1530a",
    "callsign"  : "DCM4121",
    "nnumber"   : "N1848T",
    "departure" :
    {
      "airport"             : "KI63",
      "time"                : "2019-12-11 21:05:35+00:00",
      "airport_position"    : 
      {
        "altitude"  : "734.0",
        "latitude"  : "39.98749924",
        "longitude" : "-90.80419922"
      },
      "aircraft_position"   : 
      {
        "altitude"  : "7375.0",
        "latitude"  : "39.96230303230932",
        "longitude" : "-90.91298883611506"
      },
      "horizontal_distance" : "9705.328988855574",
      "vertical_distance"   : "6641.0"
    },
    "arrival"   :
    {
      "airport"             : "KBWI",
      "time"                : "2019-12-11 22:33:52+00:00",
      "airport_position"    : 
      {
        "altitude"  : "146.0",
        "latitude"  : "39.1754",
        "longitude" : "-76.668297"
      },
      "aircraft_position"   : 
      {
        "altitude"  : "-25.0",
        "latitude"  : "39.16346663135593",
        "longitude" : "-76.641357421875"
      },
      "horizontal_distance" : "2678.661956131546",
      "vertical_distance"   : "-171.0"
    }
  },
  {
    "icao"      : "a1530a",
    "callsign"  : "DCM4121",
    "nnumber"   : "N1848T",
    "departure" :
    {
      "airport"             : "KBWI",
      "time"                : "2019-12-11 22:59:18+00:00",
      "airport_position"    : 
      {
        "altitude"  : "146.0",
        "latitude"  : "39.1754",
        "longitude" : "-76.668297"
      },
      "aircraft_position"   : 
      {
        "altitude"  : "175.0",
        "latitude"  : "39.18827819824219",
        "longitude" : "-76.66420978048575"
      },
      "horizontal_distance" : "1472.6941554950185",
      "vertical_distance"   : "29.0"
    },
    "arrival"   :
    {
      "airport"             : "63PA",
      "time"                : "2019-12-11 23:13:47+00:00",
      "airport_position"    : 
      {
        "altitude"  : "510.0",
        "latitude"  : "40.322173",
        "longitude" : "-76.100664"
      },
      "aircraft_position"   : 
      {
        "altitude"  : "2300.0000000000005",
        "latitude"  : "40.26535034179688",
        "longitude" : "-76.0811767578125"
      },
      "horizontal_distance" : "6523.537820050559",
      "vertical_distance"   : "1790.0000000000005"
    }
  },
  {
    "icao"      : "a1530a",
    "callsign"  : "DCM4121",
    "nnumber"   : "N1848T",
    "departure" :
    {
      "airport"             : "63PA",
      "time"                : "2019-12-12 12:50:08+00:00",
      "airport_position"    : 
      {
        "altitude"  : "510.0",
        "latitude"  : "40.322173",
        "longitude" : "-76.100664"
      },
      "aircraft_position"   : 
      {
        "altitude"  : "3874.9999999999995",
        "latitude"  : "40.38185119628906",
        "longitude" : "-76.10760498046875"
      },
      "horizontal_distance" : "6652.933720109794",
      "vertical_distance"   : "3364.9999999999995"
    },
    "arrival"   :
    {
      "airport"             : "32IS",
      "time"                : "2019-12-12 14:44:04+00:00",
      "airport_position"    : 
      {
        "altitude"  : "485.0",
        "latitude"  : "40.13529968261719",
        "longitude" : "-91.00959777832031"
      },
      "aircraft_position"   : 
      {
        "altitude"  : "6250.0",
        "latitude"  : "40.12765658103813",
        "longitude" : "-91.05262756347656"
      },
      "horizontal_distance" : "3764.3357377953075",
      "vertical_distance"   : "5765.0"
    }
  },
  {
    "icao"      : "a1530a",
    "callsign"  : "DCM4121",
    "nnumber"   : "N1848T",
    "departure" :
    {
      "airport"             : "KUIN",
      "time"                : "2019-12-12 21:09:30+00:00",
      "airport_position"    : 
      {
        "altitude"  : "768.0",
        "latitude"  : "39.94269943",
        "longitude" : "-91.19460297"
      },
      "aircraft_position"   : 
      {
        "altitude"  : "7724.999999999999",
        "latitude"  : "39.89849853515625",
        "longitude" : "-91.03265513544494"
      },
      "horizontal_distance" : "14689.448607395598",
      "vertical_distance"   : "6956.999999999999"
    },
    "arrival"   :
    {
      "airport"             : "3PA0",
      "time"                : "2019-12-12 22:29:23+00:00",
      "airport_position"    : 
      {
        "altitude"  : "450.0",
        "latitude"  : "40.383399963378906",
        "longitude" : "-76.46640014648438"
      },
      "aircraft_position"   : 
      {
        "altitude"  : "1099.9999999999998",
        "latitude"  : "40.418468410685904",
        "longitude" : "-76.05329340154475"
      },
      "horizontal_distance" : "35285.09492826994",
      "vertical_distance"   : "649.9999999999998"
    }
  },
  {
    "icao"      : "a1530a",
    "callsign"  : "DCM4121",
    "nnumber"   : "N1848T",
    "departure" :
    {
      "airport"             : "63PA",
      "time"                : "2019-12-12 23:17:58+00:00",
      "airport_position"    : 
      {
        "altitude"  : "510.0",
        "latitude"  : "40.322173",
        "longitude" : "-76.100664"
      },
      "aircraft_position"   : 
      {
        "altitude"  : "4650.0",
        "latitude"  : "40.28704833984375",
        "longitude" : "-76.05035400390625"
      },
      "horizontal_distance" : "5788.3391203672045",
      "vertical_distance"   : "4140.0"
    },
    "arrival"   :
    {
      "airport"             : "30LL",
      "time"                : "2019-12-13 01:05:50+00:00",
      "airport_position"    : 
      {
        "altitude"  : "614.0",
        "latitude"  : "39.75419998168945",
        "longitude" : "-90.36540222167969"
      },
      "aircraft_position"   : 
      {
        "altitude"  : "2250.0000000000005",
        "latitude"  : "39.7225341796875",
        "longitude" : "-90.69655708644702"
      },
      "horizontal_distance" : "28603.106435252954",
      "vertical_distance"   : "1636.0000000000005"
    }
  },
  {
    "icao"      : "a1530a",
    "callsign"  : "DCM4121",
    "nnumber"   : "N1848T",
    "departure" :
    {
      "airport"             : "KUIN",
      "time"                : "2019-12-26 23:32:24+00:00",
      "airport_position"    : 
      {
        "altitude"  : "768.0",
        "latitude"  : "39.94269943",
        "longitude" : "-91.19460297"
      },
      "aircraft_position"   : 
      {
        "altitude"  : "6825.0",
        "latitude"  : "39.868034750728285",
        "longitude" : "-91.1849365234375"
      },
      "horizontal_distance" : "8331.336118848158",
      "vertical_distance"   : "6057.0"
    },
    "arrival"   :
    {
      "airport"             : "KAPF",
      "time"                : "2019-12-27 01:45:53+00:00",
      "airport_position"    : 
      {
        "altitude"  : "8.0",
        "latitude"  : "26.1525993347",
        "longitude" : "-81.7752990723"
      },
      "aircraft_position"   : 
      {
        "altitude"  : "2375.0000000000005",
        "latitude"  : "26.13002014160156",
        "longitude" : "-81.94681419516508"
      },
      "horizontal_distance" : "17332.574839344965",
      "vertical_distance"   : "2367.0000000000005"
    }
  },
  {
    "icao"      : "a1530a",
    "callsign"  : "DCM4121",
    "nnumber"   : "N1848T",
    "departure" :
    {
      "airport"             : "KAPF",
      "time"                : "2019-12-27 02:30:45+00:00",
      "airport_position"    : 
      {
        "altitude"  : "8.0",
        "latitude"  : "26.1525993347",
        "longitude" : "-81.7752990723"
      },
      "aircraft_position"   : 
      {
        "altitude"  : "4325.0",
        "latitude"  : "26.20596313476562",
        "longitude" : "-81.71765597361441"
      },
      "horizontal_distance" : "8255.814295478742",
      "vertical_distance"   : "4317.0"
    },
    "arrival"   :
    {
      "airport"             : "44IS",
      "time"                : "2019-12-27 04:43:24+00:00",
      "airport_position"    : 
      {
        "altitude"  : "700.0",
        "latitude"  : "39.74480056762695",
        "longitude" : "-91.07489776611328"
      },
      "aircraft_position"   : 
      {
        "altitude"  : "4975.0",
        "latitude"  : "39.71841430664062",
        "longitude" : "-90.9518100904382"
      },
      "horizontal_distance" : "10951.111952131881",
      "vertical_distance"   : "4275.0"
    }
  }
]